Metadata-Version: 2.1
Name: dep2pict-gui
Version: 0.7.0
Summary: A Qt interface for the dep2pict software
Home-page: http://dep2pict.loria.fr
Author: bguil
Author-email: Bruno.Guillaume@loria.fr
License: LICENSE/Licence_CeCILL_V2-en.txt
Platform: UNKNOWN
